odoo/addons/hr_expense_pay_to_vendor/README.rst
odoo/addons/hr_expense_pay_to_vendor/__init__.py
odoo/addons/hr_expense_pay_to_vendor/__manifest__.py
odoo/addons/hr_expense_pay_to_vendor/i18n/es.po
odoo/addons/hr_expense_pay_to_vendor/i18n/hr_expense_pay_to_vendor.pot
odoo/addons/hr_expense_pay_to_vendor/i18n/it.po
odoo/addons/hr_expense_pay_to_vendor/models/__init__.py
odoo/addons/hr_expense_pay_to_vendor/models/hr_expense.py
odoo/addons/hr_expense_pay_to_vendor/readme/CONTRIBUTORS.rst
odoo/addons/hr_expense_pay_to_vendor/readme/DESCRIPTION.rst
odoo/addons/hr_expense_pay_to_vendor/readme/USAGE.rst
odoo/addons/hr_expense_pay_to_vendor/static/description/icon.png
odoo/addons/hr_expense_pay_to_vendor/static/description/index.html
odoo/addons/hr_expense_pay_to_vendor/tests/__init__.py
odoo/addons/hr_expense_pay_to_vendor/tests/test_hr_expense_pay_to_vendor.py
odoo/addons/hr_expense_pay_to_vendor/views/hr_expense_views.xml
odoo14_addon_hr_expense_pay_to_vendor-14.0.1.0.1.dev10.dist-info/METADATA
odoo14_addon_hr_expense_pay_to_vendor-14.0.1.0.1.dev10.dist-info/WHEEL
odoo14_addon_hr_expense_pay_to_vendor-14.0.1.0.1.dev10.dist-info/top_level.txt
odoo14_addon_hr_expense_pay_to_vendor-14.0.1.0.1.dev10.dist-info/RECORD
